BCD_divisible_by_3.v
module BCD_divisible_by_3(D, Q);
	input wire [15:0] D;	// 4 digit BCD number (fourth_digit, third_digit, second_digit, first_digit)
	
	output Q;			// 1 bit output
	reg result;
	
	reg [3:0] first_digit;	// store each BCD digit
	reg [3:0] second_digit;
	reg [3:0] third_digit;
	reg [3:0] fourth_digit;	
	
	reg [4:0] sum_first_second; // two 5-bit variables to store intermediate sums
	reg [4:0] sum_third_fourth;
	reg [5:0] sum_final; // 6-bit final sum: (first_digit + second_digit) + (third_digit + fourth_digit)
	
	// sum bits
	reg s1, s2, s3, s4;	// for sum_first_second
	reg s5, s6, s7, s8;	// for sum_third_fourth
	reg s9, s10, s11, s12, s13;	// for sum_final
		
	// carry bits
	reg c1, c2, c3, c4;	// for sum_first_second
	reg c5, c6, c7, c8;	// for sum_third_fourth
	reg c9, c10, c11, c12, c13;	// for sum_final
	

	always @ (D)
	begin
		first_digit = D[3:0];	// get each digit
		second_digit = D[7:4];
		third_digit = D[11:8];
		fourth_digit = D[15:12];
		
		// calculate first_digit + second_digit
		s1 = first_digit[0] ^ second_digit[0];
		c1 = first_digit[0] & second_digit[0];	
		
		s2 = first_digit[1] ^ second_digit[1] ^ c1;
		c2 = (first_digit[1] & second_digit[1]) || (first_digit[1] & c1) || (c1 & second_digit[1]);
		
		s3 = first_digit[2] ^ second_digit[2] ^ c2;
		c3 = (first_digit[2] & second_digit[2]) || (first_digit[2] & c2) || (c2 & second_digit[2]);
		
		s4 = first_digit[3] ^ second_digit[3] ^ c3;
		c4 = (first_digit[3] & second_digit[3]) || (first_digit[3] & c3) || (c3 & second_digit[3]);
		
		sum_first_second = {c4, s4, s3, s2, s1};

																	
		// calculate third_digit + fourth_digit
		
		s5 = third_digit[0] ^ fourth_digit[0];	
		c5 = third_digit[0] & fourth_digit[0];	
		
		s6 = third_digit[1] ^ fourth_digit[1] ^ c5;
		c6 = (third_digit[1] & fourth_digit[1]) || (third_digit[1] & c5) || (c5 & fourth_digit[1]);
				
		s7 = third_digit[2] ^ fourth_digit[2] ^ c6;
		c7 = (third_digit[2] & fourth_digit[2]) || (third_digit[2] & c6) || (c6 & fourth_digit[2]);
		
		s8 = third_digit[3] ^ fourth_digit[3] ^ c7;
		c8 = (third_digit[3] & fourth_digit[3]) || (third_digit[3] & c7) || (c7 & fourth_digit[3]);
		
		sum_third_fourth = {c8, s8, s7, s6, s5};
		
		
		// calculate sum_final
		
		s9 = sum_first_second[0] ^ sum_third_fourth[0];
		c9 = sum_first_second[0] & sum_third_fourth[0];
		
		s10 = sum_first_second[1] ^ sum_third_fourth[1] ^ c9;
		c10 = (sum_first_second[1] & sum_third_fourth[1]) || (sum_first_second[1] & c9) || (c9 & sum_third_fourth[1]);
		
		s11 = sum_first_second[2] ^ sum_third_fourth[2] ^ c10;
		c11 = (sum_first_second[2] & sum_third_fourth[2]) || (sum_first_second[2] & c10) || (c10 & sum_third_fourth[2]);
		
		s12 = sum_first_second[3] ^ sum_third_fourth[3] ^ c11;
		c12 = (sum_first_second[3] & sum_third_fourth[3]) || (sum_first_second[3] & c11) || (c11 & sum_third_fourth[3]);
		
		s13 = sum_first_second[4] ^ sum_third_fourth[4] ^ c12;
		c13 = (sum_first_second[4] & sum_third_fourth[4]) || (sum_first_second[4] & c12) || (c12 & sum_third_fourth[4]);
		
		sum_final = {c13, s13, s12, s11, s10, s9};	
		// final sum of all 4 BCD digits
		// max value = (9 + 9 + 9 + 9) = 36 = 6'b100100												
		// multiples of 3 between 0 and 36:
		// 0, 3, 6, 9, 12, 15, 18, 21, 24, 27, 30, 33, 36
		
		result = (sum_final == 6'b000000) || (sum_final == 6'b000011) || (sum_final == 6'b000110) || (sum_final == 6'b001001) || (sum_final == 6'b001100) || (sum_final == 6'b001111) || (sum_final == 6'b010010) || (sum_final == 6'b010101) || (sum_final == 6'b000000) || (sum_final == 6'b011000) || (sum_final == 6'b011011) || (sum_final == 6'b011110) || (sum_final == 6'b100001) || (sum_final == 6'b100100);
		
	end
	
	assign Q = result;
	
endmodule

BCD_divisible_by_3_tb.v
`timescale 1ns / 1ns
`include "BCD_divisible_by_3.v"

module BCD_divisible_by_3_tb;

	// Inputs
	reg [15:0] D;

	// Outputs
	wire Q;

	// Instantiate the Unit Under Test (UUT)
	BCD_divisible_by_3 uut (
		.D(D), 
		.Q(Q)
	);
	

	initial begin
		$dumpfile("test_tb_2.vcd");
    	$dumpvars(0, BCD_divisible_by_3_tb);

		// Initialize Inputs
		D = 0;

		// Wait 100 ns for global reset to finish
		#100;
        
		// Add stimulus here
		
		// not divisible
		D = 16'h0001;	//1
		#10;

		D = 16'h1234;   // 1234
		#10;
		
		D = 16'h8314;	// 8314
		#10;
		
		D = 16'h1111;	// 1111
		#10;
		
		D = 16'h2222;	// 2222
		#10;
		
		D = 16'h5248;	// 5248
		#10;
		
		D = 16'h9998;	// 9998
		#10;
		
		D = 16'h9002;	// 9002
		#10;
		
		D = 16'h5041;	// 5041
		#10;
			
		D = 16'h1337;	// 1337
		#10;
				
				
				
		// divisible
		D = 16'h0000;	//0
		#10;
				
		D = 16'h0003;	//3
		#10;
		
		D = 16'h9999;	// 9999
		#10;
		
		D = 16'h9909;	// 9909
		#10;
		
		D = 16'h9090;	// 9090
		#10;
		
		D = 16'h1521;   // 1521
		#10;
		
		D = 16'h2214;	// 2214
		#10;

		D = 16'h3333;	// 3333
		#10;	
		
		D = 16'h8316;	// 8316
		#10;
		
		D = 16'h5043;	// 5043
		#1000;
		
		$finish;
  
	end
      
endmodule

test_tb_2.vcd
$date
	Fri Jan 07 14:44:58 2022
$end
$version
	Icarus Verilog
$end
$timescale
	1ns
$end
$scope module BCD_divisible_by_3_tb $end
$var wire 1 ! Q $end
$var reg 16 " D [15:0] $end
$scope module uut $end
$var wire 16 # D [15:0] $end
$var wire 1 ! Q $end
$var reg 1 $ c1 $end
$var reg 1 % c10 $end
$var reg 1 & c11 $end
$var reg 1 ' c12 $end
$var reg 1 ( c13 $end
$var reg 1 ) c2 $end
$var reg 1 * c3 $end
$var reg 1 + c4 $end
$var reg 1 , c5 $end
$var reg 1 - c6 $end
$var reg 1 . c7 $end
$var reg 1 / c8 $end
$var reg 1 0 c9 $end
$var reg 4 1 first_digit [3:0] $end
$var reg 4 2 fourth_digit [3:0] $end
$var reg 1 3 result $end
$var reg 1 4 s1 $end
$var reg 1 5 s10 $end
$var reg 1 6 s11 $end
$var reg 1 7 s12 $end
$var reg 1 8 s13 $end
$var reg 1 9 s2 $end
$var reg 1 : s3 $end
$var reg 1 ; s4 $end
$var reg 1 < s5 $end
$var reg 1 = s6 $end
$var reg 1 > s7 $end
$var reg 1 ? s8 $end
$var reg 1 @ s9 $end
$var reg 4 A second_digit [3:0] $end
$var reg 6 B sum_final [5:0] $end
$var reg 5 C sum_first_second [4:0] $end
$var reg 5 D sum_third_fourth [4:0] $end
$var reg 4 E third_digit [3:0] $end
$upscope $end
$upscope $end
$enddefinitions $end
#0
$dumpvars
b0 E
b0 D
b0 C
b0 B
b0 A
0@
0?
0>
0=
0<
0;
0:
09
08
07
06
05
04
13
b0 2
b0 1
00
0/
0.
0-
0,
0+
0*
0)
0(
0'
0&
0%
0$
b0 #
b0 "
1!
$end
#100
0!
03
b1 B
1@
b1 C
14
b1 1
b1 "
b1 #
#110
b1010 B
17
1&
1%
15
10
0@
b11 D
1=
1<
b111 C
1:
19
b1 2
b10 E
b11 A
b100 1
b1001000110100 "
b1001000110100 #
#120
b10000 B
18
1'
07
05
b1011 D
1?
b101 C
09
b1000 2
b11 E
b1 A
b1000001100010100 "
b1000001100010100 #
#130
b100 B
08
0'
0&
16
00
b10 D
0?
1,
0<
b10 C
0:
19
1$
04
b1 2
b1 E
b1 1
b1000100010001 "
b1000100010001 #
#140
b1000 B
17
1&
06
0%
b100 D
1>
1-
0=
0,
b100 C
1:
1)
09
0$
b10 2
b10 E
b10 A
b10 1
b10001000100010 "
b10001000100010 #
#150
b10011 B
18
1'
07
15
1@
b111 D
0-
1=
1<
b1100 C
1;
0)
b101 2
b100 A
b1000 1
b101001001001000 "
b101001001001000 #
#160
b100011 B
1(
08
0'
0&
b10010 D
1/
0>
1,
0<
b10001 C
1+
0;
0:
14
b1001 2
b1001 E
b1001 A
b1001100110011000 "
b1001100110011000 #
#170
b1011 B
0(
17
b1001 D
0/
1?
0=
0,
1<
b10 C
0+
19
04
b0 E
b0 A
b10 1
b1001000000000010 "
b1001000000000010 #
#180
b1010 B
1&
10
0@
b101 D
0?
1>
b101 C
1:
09
14
b101 2
b100 A
b1 1
b101000001000001 "
b101000001000001 #
#190
b1110 B
0&
16
00
b100 D
1-
1,
0<
b1010 C
1;
1*
0:
1)
19
1$
04
b1 2
b11 E
b11 A
b111 1
b1001100110111 "
b1001100110111 #
#200
1!
13
b0 B
07
06
05
b0 D
0>
0-
0,
b0 C
0;
0*
0)
09
0$
b0 2
b0 E
b0 A
b0 1
b0 "
b0 #
#210
b11 B
15
1@
b11 C
19
14
b11 1
b11 "
b11 #
#220
b100100 B
1(
16
1%
05
0@
b10010 D
1/
1=
1,
b10010 C
1+
1$
04
b1001 2
b1001 E
b1001 A
b1001 1
b1001100110011001 "
b1001100110011001 #
#230
b11011 B
0(
18
17
06
0%
15
1@
b1001 C
0+
1;
09
0$
14
b0 A
b1001100100001001 "
b1001100100001001 #
#240
b10010 B
1'
07
10
0@
b1001 D
0/
1?
0=
0,
1<
b0 E
b1001 A
b0 1
b1001000010010000 "
b1001000010010000 #
#250
b1001 B
08
0'
17
1&
1%
05
00
1@
b110 D
0?
1>
1=
1,
0<
b11 C
0;
19
b1 2
b101 E
b10 A
b1 1
b1010100100001 "
b1010100100001 #
#260
0%
b100 D
1-
0=
0,
b101 C
1:
09
b10 2
b10 E
b1 A
b100 1
b10001000010100 "
b10001000010100 #
#270
b1100 B
16
1%
0@
b110 D
1=
1,
b110 C
1)
19
1$
04
b11 2
b11 E
b11 A
b11 1
b11001100110011 "
b11001100110011 #
#280
b10010 B
18
1'
07
06
15
10
b1011 D
1?
0>
0-
0,
1<
b111 C
0)
0$
14
b1000 2
b1 A
b110 1
b1000001100010110 "
b1000001100010110 #
#290
b1100 B
08
0'
17
16
05
b101 D
0?
1>
0=
b101 2
b0 E
b100 A
b11 1
b101000001000011 "
b101000001000011 #
