single_digit_adder.v
module single_digit_adder (D1, D2, Cin, Cout, Out);

    input D1, D2, Cin; // input 1, 2, and carry in
    output Cout, Out; // output and carry out

    wire D12, D1C, D2C; // for calculating carry out

    xor(Out, D1, D2, Cin); // calculate output
    and(D12, D1, D2);
    and(D1C, D1, Cin);
    and(D2C, D2, Cin);
    or(Cout, D12, D1C, D2C);

endmodule

six_digit_adder.v
`include "single_digit_adder.v"

module six_digit_adder (D1, D2, Cout, Out);

    input [5:0] D1, D2; // input 1, 2, and carry in
    output [5:0] Out; // output and carry out
    output Cout; 
    wire carry[4:0]; 

    single_digit_adder dig0 (D1[0], D2[0], 1'b0, carry[0], Out[0]);
    single_digit_adder dig1 (D1[1], D2[1], carry[0], carry[1], Out[1]);
    single_digit_adder dig2 (D1[2], D2[2], carry[1], carry[2], Out[2]);
    single_digit_adder dig3 (D1[3], D2[3], carry[2], carry[3], Out[3]);
    single_digit_adder dig4 (D1[4], D2[4], carry[3], carry[4], Out[4]);
    single_digit_adder dig5 (D1[5], D2[5], carry[4], Cout, Out[5]);

endmodule

BCD_divisible_by_11.v
`include "six_digit_adder.v"

module BCD_divisible_by_11 (D, Q);

    input [15:0] D; // input 1, 2, and carry in
    output Q; // output and carry out

    wire [5:0] a, b1, b2, b3, c, d1, d2, d3; // extend each number to 6 bits
    wire c1, c2, c3, c4, c5; // carry

    wire [5:0] sum1, sum2, sum3; // sums
    wire mult1, mult2, mult3; 
    wire [4:0] negation;

    // load each digit as a 6 digit binary number
    assign a = {2'b00, D[15:12]};
    assign b1 = {2'b00, D[11:8]};
    assign c = {2'b00, D[7:4]};
    assign d1 = {2'b00, D[3:0]};

    // perform 2's complement on the second and last digit
    not(b2[0], b1[0]);
    not(b2[1], b1[1]);
    not(b2[2], b1[2]);
    not(b2[3], b1[3]);
    not(b2[4], b1[4]);
    not(b2[5], b1[5]);
    six_digit_adder add0 (b2, 6'b000001, c1, b3);
    not(d2[0], d1[0]);
    not(d2[1], d1[1]);
    not(d2[2], d1[2]);
    not(d2[3], d1[3]);
    not(d2[4], d1[4]);
    not(d2[5], d1[5]);
    six_digit_adder add1 (d2, 6'b000001, c2, d3);

    // add all 4 numbers
    six_digit_adder add2 (a, b3, c3, sum1);
    six_digit_adder add3 (sum1, c, c4, sum2);
    six_digit_adder add4 (sum2, d3, c5, sum3);

    // true if all bits in sum3 are zero
    nor(mult1, sum3[0], sum3[1], sum3[2], sum3[3], sum3[4], sum3[5]);

    // true if sum is 11
    not(negation[0], sum3[5]);
    not(negation[1], sum3[4]);
    not(negation[2], sum3[2]);
    and(mult2, sum3[0], sum3[1], negation[2], sum3[3], negation[1], negation[0]);

    // true if sum is -11
    not(negation[3], sum3[3]);
    not(negation[4], sum3[1]);
    and(mult3, sum3[0], negation[4], sum3[2], negation[3], sum3[4], sum3[5]);

    // Q is true if sum is equal to either 0, 11, or -11
    or(Q, mult1, mult2, mult3);
endmodule

BCD_divisible_by_11_tb.v
`timescale 1ns / 1ns
`include "BCD_divisible_by_11.v"

module BCD_divisible_by_11_tb;

    reg [15:0] D; // data
    wire Q; // output

BCD_divisible_by_11 uut(D, Q);

initial begin
    
    $dumpfile("test_tb_3.vcd");
    $dumpvars(0, BCD_divisible_by_11_tb);

    // not divisible
    D = 16'h2121;
    #20;

    // not divisible
    D = 16'h2122;
    #20;

    // not divisible
    D = 16'h3111;
    #20;

    // not divisible
    D = 16'h5000;
    #20;

        // not divisible
    D = 16'h0500;
    #20;

        // not divisible
    D = 16'h0050;
    #20;


    // not divisible
    D = 16'h0005;
    #20;

    // not divisible
    D = 16'h9090;
    #20;

    // not divisible
    D = 16'h0909;
    #20;

    // divisible
    D = 16'h7777;
    #20;

    // divisible
    D = 16'h0000;
    #20;

        // divisible
    D = 16'h9999;
    #20;

    // divisible
    D = 16'h9119;
    #20;

    // divisible
    D = 16'h9240;
    #20;

    // divisible
    D = 16'h8272;
    #20;

    // divisible
    D = 16'h0704;
    #20;

    $display("test complete");

end

endmodule

test_tb_3.vcd
$date
	Fri Jan 07 14:47:35 2022
$end
$version
	Icarus Verilog
$end
$timescale
	1ns
$end
$scope module BCD_divisible_by_11_tb $end
$var wire 1 ! Q $end
$var reg 16 " D [15:0] $end
$scope module uut $end
$var wire 16 # D [15:0] $end
$var wire 1 ! Q $end
$var wire 1 $ mult1 $end
$var wire 1 % mult2 $end
$var wire 1 & mult3 $end
$var wire 6 ' sum3 [5:0] $end
$var wire 6 ( sum2 [5:0] $end
$var wire 6 ) sum1 [5:0] $end
$var wire 5 * negation [4:0] $end
$var wire 6 + d3 [5:0] $end
$var wire 6 , d2 [5:0] $end
$var wire 6 - d1 [5:0] $end
$var wire 1 . c5 $end
$var wire 1 / c4 $end
$var wire 1 0 c3 $end
$var wire 1 1 c2 $end
$var wire 1 2 c1 $end
$var wire 6 3 c [5:0] $end
$var wire 6 4 b3 [5:0] $end
$var wire 6 5 b2 [5:0] $end
$var wire 6 6 b1 [5:0] $end
$var wire 6 7 a [5:0] $end
$scope module add0 $end
$var wire 6 8 D1 [5:0] $end
$var wire 6 9 D2 [5:0] $end
$var wire 6 : Out [5:0] $end
$var wire 1 2 Cout $end
$scope module dig0 $end
$var wire 1 ; Cin $end
$var wire 1 < Cout $end
$var wire 1 = D1 $end
$var wire 1 > D12 $end
$var wire 1 ? D1C $end
$var wire 1 @ D2 $end
$var wire 1 A D2C $end
$var wire 1 B Out $end
$upscope $end
$scope module dig1 $end
$var wire 1 < Cin $end
$var wire 1 C Cout $end
$var wire 1 D D1 $end
$var wire 1 E D12 $end
$var wire 1 F D1C $end
$var wire 1 G D2 $end
$var wire 1 H D2C $end
$var wire 1 I Out $end
$upscope $end
$scope module dig2 $end
$var wire 1 C Cin $end
$var wire 1 J Cout $end
$var wire 1 K D1 $end
$var wire 1 L D12 $end
$var wire 1 M D1C $end
$var wire 1 N D2 $end
$var wire 1 O D2C $end
$var wire 1 P Out $end
$upscope $end
$scope module dig3 $end
$var wire 1 J Cin $end
$var wire 1 Q Cout $end
$var wire 1 R D1 $end
$var wire 1 S D12 $end
$var wire 1 T D1C $end
$var wire 1 U D2 $end
$var wire 1 V D2C $end
$var wire 1 W Out $end
$upscope $end
$scope module dig4 $end
$var wire 1 Q Cin $end
$var wire 1 X Cout $end
$var wire 1 Y D1 $end
$var wire 1 Z D12 $end
$var wire 1 [ D1C $end
$var wire 1 \ D2 $end
$var wire 1 ] D2C $end
$var wire 1 ^ Out $end
$upscope $end
$scope module dig5 $end
$var wire 1 X Cin $end
$var wire 1 2 Cout $end
$var wire 1 _ D1 $end
$var wire 1 ` D12 $end
$var wire 1 a D1C $end
$var wire 1 b D2 $end
$var wire 1 c D2C $end
$var wire 1 d Out $end
$upscope $end
$upscope $end
$scope module add1 $end
$var wire 6 e D1 [5:0] $end
$var wire 6 f D2 [5:0] $end
$var wire 6 g Out [5:0] $end
$var wire 1 1 Cout $end
$scope module dig0 $end
$var wire 1 h Cin $end
$var wire 1 i Cout $end
$var wire 1 j D1 $end
$var wire 1 k D12 $end
$var wire 1 l D1C $end
$var wire 1 m D2 $end
$var wire 1 n D2C $end
$var wire 1 o Out $end
$upscope $end
$scope module dig1 $end
$var wire 1 i Cin $end
$var wire 1 p Cout $end
$var wire 1 q D1 $end
$var wire 1 r D12 $end
$var wire 1 s D1C $end
$var wire 1 t D2 $end
$var wire 1 u D2C $end
$var wire 1 v Out $end
$upscope $end
$scope module dig2 $end
$var wire 1 p Cin $end
$var wire 1 w Cout $end
$var wire 1 x D1 $end
$var wire 1 y D12 $end
$var wire 1 z D1C $end
$var wire 1 { D2 $end
$var wire 1 | D2C $end
$var wire 1 } Out $end
$upscope $end
$scope module dig3 $end
$var wire 1 w Cin $end
$var wire 1 ~ Cout $end
$var wire 1 !" D1 $end
$var wire 1 "" D12 $end
$var wire 1 #" D1C $end
$var wire 1 $" D2 $end
$var wire 1 %" D2C $end
$var wire 1 &" Out $end
$upscope $end
$scope module dig4 $end
$var wire 1 ~ Cin $end
$var wire 1 '" Cout $end
$var wire 1 (" D1 $end
$var wire 1 )" D12 $end
$var wire 1 *" D1C $end
$var wire 1 +" D2 $end
$var wire 1 ," D2C $end
$var wire 1 -" Out $end
$upscope $end
$scope module dig5 $end
$var wire 1 '" Cin $end
$var wire 1 1 Cout $end
$var wire 1 ." D1 $end
$var wire 1 /" D12 $end
$var wire 1 0" D1C $end
$var wire 1 1" D2 $end
$var wire 1 2" D2C $end
$var wire 1 3" Out $end
$upscope $end
$upscope $end
$scope module add2 $end
$var wire 6 4" D1 [5:0] $end
$var wire 6 5" D2 [5:0] $end
$var wire 6 6" Out [5:0] $end
$var wire 1 0 Cout $end
$scope module dig0 $end
$var wire 1 7" Cin $end
$var wire 1 8" Cout $end
$var wire 1 9" D1 $end
$var wire 1 :" D12 $end
$var wire 1 ;" D1C $end
$var wire 1 <" D2 $end
$var wire 1 =" D2C $end
$var wire 1 >" Out $end
$upscope $end
$scope module dig1 $end
$var wire 1 8" Cin $end
$var wire 1 ?" Cout $end
$var wire 1 @" D1 $end
$var wire 1 A" D12 $end
$var wire 1 B" D1C $end
$var wire 1 C" D2 $end
$var wire 1 D" D2C $end
$var wire 1 E" Out $end
$upscope $end
$scope module dig2 $end
$var wire 1 ?" Cin $end
$var wire 1 F" Cout $end
$var wire 1 G" D1 $end
$var wire 1 H" D12 $end
$var wire 1 I" D1C $end
$var wire 1 J" D2 $end
$var wire 1 K" D2C $end
$var wire 1 L" Out $end
$upscope $end
$scope module dig3 $end
$var wire 1 F" Cin $end
$var wire 1 M" Cout $end
$var wire 1 N" D1 $end
$var wire 1 O" D12 $end
$var wire 1 P" D1C $end
$var wire 1 Q" D2 $end
$var wire 1 R" D2C $end
$var wire 1 S" Out $end
$upscope $end
$scope module dig4 $end
$var wire 1 M" Cin $end
$var wire 1 T" Cout $end
$var wire 1 U" D1 $end
$var wire 1 V" D12 $end
$var wire 1 W" D1C $end
$var wire 1 X" D2 $end
$var wire 1 Y" D2C $end
$var wire 1 Z" Out $end
$upscope $end
$scope module dig5 $end
$var wire 1 T" Cin $end
$var wire 1 0 Cout $end
$var wire 1 [" D1 $end
$var wire 1 \" D12 $end
$var wire 1 ]" D1C $end
$var wire 1 ^" D2 $end
$var wire 1 _" D2C $end
$var wire 1 `" Out $end
$upscope $end
$upscope $end
$scope module add3 $end
$var wire 6 a" D1 [5:0] $end
$var wire 6 b" D2 [5:0] $end
$var wire 6 c" Out [5:0] $end
$var wire 1 / Cout $end
$scope module dig0 $end
$var wire 1 d" Cin $end
$var wire 1 e" Cout $end
$var wire 1 f" D1 $end
$var wire 1 g" D12 $end
$var wire 1 h" D1C $end
$var wire 1 i" D2 $end
$var wire 1 j" D2C $end
$var wire 1 k" Out $end
$upscope $end
$scope module dig1 $end
$var wire 1 e" Cin $end
$var wire 1 l" Cout $end
$var wire 1 m" D1 $end
$var wire 1 n" D12 $end
$var wire 1 o" D1C $end
$var wire 1 p" D2 $end
$var wire 1 q" D2C $end
$var wire 1 r" Out $end
$upscope $end
$scope module dig2 $end
$var wire 1 l" Cin $end
$var wire 1 s" Cout $end
$var wire 1 t" D1 $end
$var wire 1 u" D12 $end
$var wire 1 v" D1C $end
$var wire 1 w" D2 $end
$var wire 1 x" D2C $end
$var wire 1 y" Out $end
$upscope $end
$scope module dig3 $end
$var wire 1 s" Cin $end
$var wire 1 z" Cout $end
$var wire 1 {" D1 $end
$var wire 1 |" D12 $end
$var wire 1 }" D1C $end
$var wire 1 ~" D2 $end
$var wire 1 !# D2C $end
$var wire 1 "# Out $end
$upscope $end
$scope module dig4 $end
$var wire 1 z" Cin $end
$var wire 1 ## Cout $end
$var wire 1 $# D1 $end
$var wire 1 %# D12 $end
$var wire 1 &# D1C $end
$var wire 1 '# D2 $end
$var wire 1 (# D2C $end
$var wire 1 )# Out $end
$upscope $end
$scope module dig5 $end
$var wire 1 ## Cin $end
$var wire 1 / Cout $end
$var wire 1 *# D1 $end
$var wire 1 +# D12 $end
$var wire 1 ,# D1C $end
$var wire 1 -# D2 $end
$var wire 1 .# D2C $end
$var wire 1 /# Out $end
$upscope $end
$upscope $end
$scope module add4 $end
$var wire 6 0# D1 [5:0] $end
$var wire 6 1# D2 [5:0] $end
$var wire 6 2# Out [5:0] $end
$var wire 1 . Cout $end
$scope module dig0 $end
$var wire 1 3# Cin $end
$var wire 1 4# Cout $end
$var wire 1 5# D1 $end
$var wire 1 6# D12 $end
$var wire 1 7# D1C $end
$var wire 1 8# D2 $end
$var wire 1 9# D2C $end
$var wire 1 :# Out $end
$upscope $end
$scope module dig1 $end
$var wire 1 4# Cin $end
$var wire 1 ;# Cout $end
$var wire 1 <# D1 $end
$var wire 1 =# D12 $end
$var wire 1 ># D1C $end
$var wire 1 ?# D2 $end
$var wire 1 @# D2C $end
$var wire 1 A# Out $end
$upscope $end
$scope module dig2 $end
$var wire 1 ;# Cin $end
$var wire 1 B# Cout $end
$var wire 1 C# D1 $end
$var wire 1 D# D12 $end
$var wire 1 E# D1C $end
$var wire 1 F# D2 $end
$var wire 1 G# D2C $end
$var wire 1 H# Out $end
$upscope $end
$scope module dig3 $end
$var wire 1 B# Cin $end
$var wire 1 I# Cout $end
$var wire 1 J# D1 $end
$var wire 1 K# D12 $end
$var wire 1 L# D1C $end
$var wire 1 M# D2 $end
$var wire 1 N# D2C $end
$var wire 1 O# Out $end
$upscope $end
$scope module dig4 $end
$var wire 1 I# Cin $end
$var wire 1 P# Cout $end
$var wire 1 Q# D1 $end
$var wire 1 R# D12 $end
$var wire 1 S# D1C $end
$var wire 1 T# D2 $end
$var wire 1 U# D2C $end
$var wire 1 V# Out $end
$upscope $end
$scope module dig5 $end
$var wire 1 P# Cin $end
$var wire 1 . Cout $end
$var wire 1 W# D1 $end
$var wire 1 X# D12 $end
$var wire 1 Y# D1C $end
$var wire 1 Z# D2 $end
$var wire 1 [# D2C $end
$var wire 1 \# Out $end
$upscope $end
$upscope $end
$upscope $end
$upscope $end
$enddefinitions $end
#0
$dumpvars
0\#
1[#
1Z#
0Y#
0X#
0W#
0V#
1U#
1T#
0S#
0R#
0Q#
1P#
0O#
1N#
1M#
0L#
0K#
0J#
1I#
0H#
1G#
1F#
0E#
0D#
0C#
1B#
1A#
1@#
1?#
1>#
1=#
1<#
1;#
0:#
09#
18#
07#
16#
15#
14#
03#
b10 2#
b111111 1#
b11 0#
0/#
0.#
0-#
0,#
0+#
0*#
0)#
0(#
0'#
0&#
0%#
0$#
0##
0"#
0!#
0~"
0}"
0|"
0{"
0z"
0y"
0x"
0w"
0v"
0u"
0t"
0s"
1r"
0q"
1p"
0o"
0n"
0m"
0l"
1k"
0j"
0i"
0h"
0g"
1f"
0e"
0d"
b11 c"
b10 b"
b1 a"
0`"
1_"
1^"
0]"
0\"
0["
0Z"
1Y"
1X"
0W"
0V"
0U"
1T"
0S"
1R"
1Q"
0P"
0O"
0N"
1M"
0L"
1K"
1J"
0I"
0H"
0G"
1F"
0E"
0D"
1C"
0B"
1A"
1@"
1?"
1>"
0="
1<"
0;"
0:"
09"
08"
07"
b1 6"
b111111 5"
b10 4"
13"
02"
01"
00"
0/"
1."
1-"
0,"
0+"
0*"
0)"
1("
0'"
1&"
0%"
0$"
0#"
0""
1!"
0~
1}
0|
0{
0z
0y
1x
0w
1v
0u
0t
0s
0r
1q
0p
1o
0n
1m
0l
0k
0j
0i
0h
b111111 g
b1 f
b111110 e
1d
0c
0b
0a
0`
1_
1^
0]
0\
0[
0Z
1Y
0X
1W
0V
0U
0T
0S
1R
0Q
1P
0O
0N
0M
0L
1K
0J
1I
0H
0G
0F
0E
1D
0C
1B
0A
1@
0?
0>
0=
0<
0;
b111111 :
b1 9
b111110 8
b10 7
b1 6
b111110 5
b111111 4
b10 3
02
01
10
0/
1.
b1 -
b111110 ,
b111111 +
b1111 *
b1 )
b11 (
b10 '
0&
0%
0$
b10000100100001 #
b10000100100001 "
0!
$end
#20
0>#
b11111 *
04#
1:#
06#
b1 '
b1 2#
0A#
1=#
0@#
08#
1i
1?#
0o
1k
b111110 +
b111110 g
b111110 1#
1v
1j
0q
b111101 ,
b111101 e
b10 -
b10000100100010 "
b10000100100010 #
#40
1.
1Z#
01
0\#
1[#
13"
00"
1P#
1T#
0'"
0V#
1U#
1-"
0*"
1I#
1M#
0~
0O#
1N#
1>#
1@#
1&"
0#"
1B#
14#
1F#
0w
b1111 *
0H#
1G#
16#
1}
0z
1m"
1;#
18#
0i
1?#
0p
1E"
1B"
1D"
0:#
b10 '
b10 2#
1A#
1=#
1o
0k
b111111 +
b111111 g
b111111 1#
1v
0s
0f"
18"
15#
0e"
1<#
0j
1q
b10 )
b10 6"
b10 a"
0>"
1:"
1k"
0g"
b11 (
b11 c"
b11 0#
1r"
b111110 ,
b111110 e
19"
1i"
0p"
b11 7
b11 4"
b1 3
b1 b"
b1 -
b11000100010001 "
b11000100010001 #
#60
00
0.
0_"
0[#
0T"
0^"
12
0P#
0Z#
11
0Y"
0d
1a
0U#
03"
10"
0M"
0X"
1X
0I#
0T#
1'"
0R"
0^
1[
0!
0N#
0-"
1*"
0F"
0Q"
1Q
0$
0B#
0M#
1~
0K"
0W
1T
0&"
1#"
0?"
0J"
1J
0F#
1w
b11011 *
0D"
0P
1M
0G#
0A#
0}
1z
1f"
08"
0C"
1C
0;#
0?#
1p
0=#
1H#
0D#
0E#
1>"
0:"
0I
1F
0>#
0@#
0v
1s
0<#
1C#
0<"
1<
04#
08#
1i
0r"
1y"
b0 4
b0 :
b0 5"
0B
1>
b101 '
b101 2#
1:#
06#
b0 +
b0 g
b0 1#
0o
1k
0m"
1t"
1=
15#
1j
0E"
0A"
0B"
b101 )
b101 6"
b101 a"
1L"
0H"
0I"
b111111 5
b111111 8
b101 (
b101 c"
b101 0#
1k"
b111111 ,
b111111 e
0@"
1G"
0i"
b101 7
b101 4"
b0 6
b0 3
b0 b"
b0 -
b101000000000000 "
b101000000000000 #
#80
1\#
1W#
1V#
1/#
1Q#
1*#
1A#
1O#
1)#
1`"
1<#
1J#
1$#
1^"
02
0!
1r"
1"#
1Z"
1d
0a
0$
1m"
1{"
1X"
0X
b100 *
1E"
1S"
1^
0[
1C"
0C
1Q"
0Q
1:#
b111011 '
b111011 2#
0H#
1I
0F
1W
0T
15#
0C#
1<"
0<
0J"
0J
1k"
b111011 (
b111011 c"
b111011 0#
0y"
1B
0>
b111011 4
b111011 :
b111011 5"
0P
0M
1f"
0t"
0=
0K
1>"
b111011 )
b111011 6"
b111011 a"
0L"
b111010 5
b111010 8
09"
0G"
b0 7
b0 4"
b101 6
b10100000000 "
b10100000000 #
#100
0*#
0`"
0$#
0^"
12
0Z"
0d
1a
0\#
0{"
0X"
1X
0W#
0/
0S"
0^
1[
0V#
0/#
0,#
0Q"
1Q
0Q#
0##
0W
1T
0O#
0)#
0&#
0m"
1J
0J#
0z"
0E"
1M
0u"
0v"
0"#
0}"
0f"
0C"
1C
0t"
0s"
0>"
0I
1F
b0 )
b0 6"
b0 a"
0L"
0A#
0x"
b11011 *
0<"
1<
0J"
0<#
0l"
0B
1>
b0 4
b0 :
b0 5"
0P
1:#
0r"
0o"
b101 '
b101 2#
1H#
1=
1K
15#
0e"
1C#
b111111 5
b111111 8
1k"
0g"
b101 (
b101 c"
b101 0#
1y"
1i"
1w"
b0 6
b101 3
b101 b"
b1010000 "
b1010000 #
#120
1\#
1Z#
01
1V#
13"
00"
1T#
0'"
0!
1A#
1O#
1-"
0*"
0$
1?#
0p
1M#
0~
b100 *
1v
0s
1&"
0#"
18#
0i
0F#
0w
1:#
b111011 '
b111011 2#
0H#
1o
0k
b111011 +
b111011 g
b111011 1#
0}
0z
05#
0C#
0j
0x
0k"
b0 (
b0 c"
b0 0#
0y"
b111010 ,
b111010 e
0i"
0w"
b0 3
b0 b"
b101 -
b101 "
b101 #
#140
0Z#
11
03"
10"
0T#
1'"
0S#
0-"
1*"
0M#
1~
0N#
0&"
1#"
0B#
0.
1w
0R#
0G#
0\#
0[#
1z
1<#
1Q#
0;#
0P#
0?#
1p
1r"
1)#
1A#
0@#
b1101 *
1V#
0U#
0v
1s
0H#
1e"
1z"
04#
0I#
08#
1i
0F#
1g"
1|"
0:#
06#
b10010 '
b10010 2#
0O#
0K#
0o
1k
b0 +
b0 g
b0 1#
0}
1f"
1{"
05#
0J#
1j
1x
1>"
b1001 )
b1001 6"
b1001 a"
1S"
0k"
b10010 (
b10010 c"
b10010 0#
0"#
b111111 ,
b111111 e
19"
1N"
1i"
1~"
b1001 7
b1001 4"
b1001 3
b1001 b"
b0 -
b1001000010010000 "
b1001000010010000 #
#160
1B#
1.
1G#
1D#
1E#
1[#
1X#
1Y#
1;#
1C#
1P#
1W#
1@#
1=#
1>#
1y"
0U#
1R#
0S#
1/#
0!
14#
1t"
0I#
1*#
0%
16#
1L"
0K#
1`"
1H#
1\#
1m"
1J"
0J
1$#
1^"
02
1F#
0w
1Z#
01
1E"
1P
0M
1Z"
1d
0a
1}
0z
13"
00"
1C"
0C
1X"
0X
1?#
0p
1T#
0'"
1I
0F
1^
0[
1A#
b10 *
0V#
1v
0s
1-"
0*"
1<"
0<
0Q"
0Q
1<#
1Q#
18#
0i
0M#
0~
1B
0>
b110111 4
b110111 :
b110111 5"
0W
0T
0:#
1r"
b101110 '
b101110 2#
1O#
1)#
1o
0k
b110111 +
b110111 g
b110111 1#
0&"
0#"
1f"
0{"
0=
0R
15#
0e"
0J#
0z"
0j
0!"
1>"
b110111 )
b110111 6"
b110111 a"
0S"
b110110 5
b110110 8
1k"
0g"
b110111 (
b110111 c"
b110111 0#
0"#
0|"
b110110 ,
b110110 e
09"
0N"
0i"
0~"
b0 7
b0 4"
b1001 6
b0 3
b0 b"
b1001 -
b100100001001 "
b100100001001 #
#180
1!
1$
0\#
1.
0X#
0Y#
1[#
0W#
0/
0*#
10
1P#
0R#
0/#
0,#
0O#
0`"
1_"
0Q#
0##
0$#
1T"
0)#
0&#
0Z"
1Y"
0V#
0S#
1U#
0z"
1M"
1;#
1B#
1I#
0v"
0}"
1R"
b11111 *
0L#
0@#
0G#
0K#
1N#
0{"
0C"
0J"
1Q"
14#
0J#
0?#
0F#
1M#
1B"
0D"
1I"
0K"
0S"
0I
0P
b111001 4
b111001 :
b111001 5"
1W
0:#
16#
0q"
0A#
0=#
1>#
0x"
b0 '
b0 2#
0H#
0D#
1E#
0"#
0v
0}
b111001 +
b111001 g
b111001 1#
1&"
0f"
18"
0m"
1?"
0t"
1F"
0D
0K
1R
15#
0e"
1<#
0l"
1C#
0s"
0q
0x
1!"
0>"
1:"
0E"
0A"
b0 )
b0 6"
b0 a"
0L"
0H"
b111000 5
b111000 8
1k"
0g"
1r"
0n"
b111 (
b111 c"
b111 0#
1y"
0u"
b111000 ,
b111000 e
19"
1@"
1G"
1i"
1p"
1w"
b111 7
b111 4"
b111 6
b111 3
b111 b"
b111 -
b111011101110111 "
b111011101110111 #
#200
0^"
12
0Z#
11
0d
1a
03"
10"
0X"
1X
0T#
1'"
0X#
0^
1[
0-"
1*"
0Y#
0W#
0Q"
1Q
0.
0M#
1~
0R#
0/#
0W
1T
0\#
0[#
0&"
1#"
0S#
0Q#
0*#
00
1J
0P#
1w
0K#
0)#
0`"
0_"
1M
1!
0V#
0U#
1z
0G#
0L#
0J#
0$#
0T"
1C
1$
0I#
1p
0"#
0Z"
0Y"
1F
b11111 *
0O#
0N#
1s
0=#
0D#
0{"
0M"
0<"
1<
0C"
0J"
04#
0;#
0B#
08#
1i
0?#
0F#
0S"
0R"
0B
1>
0I
b0 4
b0 :
b0 5"
0P
0:#
06#
0A#
0>#
b0 '
b0 2#
0H#
0E#
0o
1k
0v
b0 +
b0 g
b0 1#
0}
0f"
08"
0m"
0?"
0t"
0F"
1=
1D
1K
05#
0<#
0C#
1j
1q
1x
0>"
0:"
0E"
0B"
b0 )
b0 6"
b0 a"
0L"
0I"
b111111 5
b111111 8
0k"
0r"
b0 (
b0 c"
b0 0#
0y"
b111111 ,
b111111 e
09"
0@"
0G"
0i"
0p"
0w"
b0 7
b0 4"
b0 6
b0 3
b0 b"
b0 -
b0 "
b0 #
#220
1@#
1P"
1U#
1L#
14#
1F"
1I#
10
1B#
1.
16#
1K"
0K#
1_"
1G#
1[#
1?"
1J"
0J
1T"
1^"
02
1;#
1F#
0w
1P#
1Z#
01
1D"
1P
0M
1Y"
1d
0a
1!
0=#
1}
0z
0R#
13"
00"
0<#
0Q#
18"
1C"
0C
1M"
1X"
0X
1$
1?#
0p
1T#
0'"
0r"
0)#
1:"
1I
0F
0O"
1^
0[
b11111 *
1v
0s
1-"
0*"
0e"
0z"
1<"
0<
0Q"
0Q
18#
0i
0M#
0~
0g"
0|"
1B
0>
b110111 4
b110111 :
b110111 5"
0W
0T
0:#
b0 '
b0 2#
0O#
1o
0k
b110111 +
b110111 g
b110111 1#
0&"
0#"
0f"
0{"
0=
0R
15#
1J#
0j
0!"
0>"
b0 )
b0 6"
b0 a"
0S"
b110110 5
b110110 8
1k"
b1001 (
b1001 c"
b1001 0#
1"#
b110110 ,
b110110 e
19"
1N"
1i"
1~"
b1001 7
b1001 4"
b1001 6
b1001 3
b1001 b"
b1001 -
b1001100110011001 "
b1001100110011001 #
#240
1.
1!
0\#
1[#
1{"
1$
1P#
b1000 )
b1000 6"
b1000 a"
1S"
1O"
1R"
b11111 *
0V#
1U#
1Q"
1I#
b111111 4
b111111 :
b111111 5"
1W
b0 '
b0 2#
0O#
1L#
1R
1J#
b111110 5
b111110 8
b1001 (
b1001 c"
b1001 0#
1"#
0~"
b1 6
b1 3
b1 b"
b1001000100011001 "
b1001000100011001 #
#260
0.
0[#
0P#
0Z#
11
0U#
03"
10"
1%
0I#
0T#
1'"
0L#
0-"
1*"
1s"
0{"
0B#
1~
1u"
0S"
0P"
0R"
1#"
1<#
1t"
0F"
0F#
1w
1r"
1L"
0K"
0G#
1!
0}
1z
1f"
08"
1m"
0?"
0;#
0$
0?#
1p
1>"
0:"
b111 )
b111 6"
b111 a"
1E"
0D"
1A#
0@#
b111 *
0v
1s
1O#
0K#
0N#
0<"
1<
1C"
04#
08#
1i
0M#
0B
1>
b111110 4
b111110 :
b111110 5"
1I
1:#
06#
b1011 '
b1011 2#
0H#
0D#
0E#
0o
1k
b0 +
b0 g
b0 1#
0&"
1=
0D
15#
0C#
1j
1!"
b111101 5
b111101 8
1k"
b1011 (
b1011 c"
b1011 0#
0y"
b111111 ,
b111111 e
0i"
1w"
b10 6
b100 3
b100 b"
b0 -
b1001001001000000 "
b1001001001000000 #
#280
1.
1[#
1P#
1Z#
01
1U#
13"
00"
1I#
1T#
0'"
1L#
1K#
1N#
1-"
0*"
1B#
1M#
0~
1!
0E#
1D#
0G#
1&"
0#"
1%
0;#
1F#
0w
b111 *
0H#
0=#
1}
0z
1C#
1?#
0p
1:#
0o"
0q"
b1011 '
b1011 2#
1A#
1y"
1v"
1x"
b111110 +
b111110 g
b111110 1#
1v
0s
0f"
15#
0e"
0<#
1l"
0q
b110 )
b110 6"
b110 a"
0>"
1k"
0g"
b1101 (
b1101 c"
b1101 0#
0r"
1n"
b111101 ,
b111101 e
09"
1i"
1p"
b1000 7
b1000 4"
b111 3
b111 b"
b10 -
b1000001001110010 "
b1000001001110010 #
#300
1&
0O#
1X#
1Y#
1W#
1.
1R#
1S#
1/#
1\#
1[#
0/
0m"
1Q#
1P#
0,#
0E"
1!
1)#
1V#
1U#
0##
1*#
00
1f"
0C"
0t"
0%
1I#
1K#
0&#
1`"
0_"
1>"
0I
0L"
0E#
b11000 *
0L#
0N#
1J#
0z"
1$#
0T"
1<"
0<
0J"
0;#
0s"
0B#
0?#
1p
1F#
1"#
0}"
1Z"
0Y"
1B
0>
b111001 4
b111001 :
b111001 5"
0P
1:#
0A#
0=#
0v"
b110101 '
b110101 2#
1H#
0D#
0v
1s
b111100 +
b111100 g
b111100 1#
1}
1{"
0M"
0=
0K
15#
0<#
0l"
0C#
1q
0x
b111001 )
b111001 6"
b111001 a"
1S"
0O"
b111000 5
b111000 8
1k"
0r"
0n"
b111001 (
b111001 c"
b111001 0#
0y"
0u"
0x"
b111011 ,
b111011 e
0N"
0i"
0p"
0w"
b0 7
b0 4"
b111 6
b0 3
b0 b"
b100 -
b11100000100 "
b11100000100 #
