single_digit_adder.v
module single_digit_adder (D1, D2, Cin, Cout, Out);

    input D1, D2, Cin; // input 1, 2, and carry in
    output Cout, Out; // output and carry out

    wire D12, D1C, D2C; // for calculating carry out

    xor(Out, D1, D2, Cin); // calculate output
    and(D12, D1, D2);
    and(D1C, D1, Cin);
    and(D2C, D2, Cin);
    or(Cout, D12, D1C, D2C);

endmodule

six_digit_adder.v
`include "single_digit_adder.v"

module six_digit_adder (D1, D2, Cout, Out);

    input [5:0] D1, D2; // input 1, 2, and carry in
    output [5:0] Out; // output and carry out
    output Cout; 
    wire carry[4:0]; 

    single_digit_adder dig0 (D1[0], D2[0], 1'b0, carry[0], Out[0]);
    single_digit_adder dig1 (D1[1], D2[1], carry[0], carry[1], Out[1]);
    single_digit_adder dig2 (D1[2], D2[2], carry[1], carry[2], Out[2]);
    single_digit_adder dig3 (D1[3], D2[3], carry[2], carry[3], Out[3]);
    single_digit_adder dig4 (D1[4], D2[4], carry[3], carry[4], Out[4]);
    single_digit_adder dig5 (D1[5], D2[5], carry[4], Cout, Out[5]);

endmodule

BCD_divisible_by_11.v
`include "six_digit_adder.v"

module BCD_divisible_by_11 (D, Q);

    input [15:0] D; // input 1, 2, and carry in
    output Q; // output and carry out

    wire [5:0] a, b1, b2, b3, c, d1, d2, d3; // extend each number to 6 bits
    wire c1, c2, c3, c4, c5; // carry

    wire [5:0] sum1, sum2, sum3; // sums

    // load each digit as a 6 digit binary number
    assign a = {2'b00, D[15:12]};
    assign b1 = {2'b00, D[11:8]};
    assign c = {2'b00, D[7:4]};
    assign d1 = {2'b00, D[3:0]};

    // perform 2's complement on the second and last digit
    not(b2[0], b1[0]);
    not(b2[1], b1[1]);
    not(b2[2], b1[2]);
    not(b2[3], b1[3]);
    not(b2[4], b1[4]);
    not(b2[5], b1[5]);
    six_digit_adder add0 (b2, 6'b000001, c1, b3);
    not(d2[0], d1[0]);
    not(d2[1], d1[1]);
    not(d2[2], d1[2]);
    not(d2[3], d1[3]);
    not(d2[4], d1[4]);
    not(d2[5], d1[5]);
    six_digit_adder add1 (d2, 6'b000001, c2, d3);

    // add all 4 numbers
    six_digit_adder add2 (a, b3, c3, sum1);
    six_digit_adder add3 (sum1, c, c4, sum2);
    six_digit_adder add4 (sum2, d3, c5, sum3);

    // set output to true if all bits in sum3 are zero
    nor(Q, sum3[0], sum3[1], sum3[2], sum3[3], sum3[4], sum3[5]);

endmodule

BCD_divisible_by_11_tb.v
`timescale 1ns / 1ns
`include "BCD_divisible_by_11.v"

module BCD_divisible_by_11_tb;

    reg [15:0] D; // data
    wire Q; // output

BCD_divisible_by_11 uut(D, Q);

initial begin
    
    $dumpfile("test_tb.vcd");
    $dumpvars(0, BCD_divisible_by_11_tb);

    // not divisible
    D = 16'h2121;
    #20;

    // not divisible
    D = 16'h2122;
    #20;

    // not divisible
    D = 16'h3111;
    #20;

    // not divisible
    D = 16'h5000;
    #20;

        // not divisible
    D = 16'h0500;
    #20;

        // not divisible
    D = 16'h0050;
    #20;


    // not divisible
    D = 16'h0005;
    #20;

    // not divisible
    D = 16'h9090;
    #20;

    // not divisible
    D = 16'h0909;
    #20;

    // divisible
    D = 16'h7777;
    #20;

    // divisible
    D = 16'h9119;
    #20;
   
    $display("test complete");

end

endmodule

test_tb.vcd
$date
	Thu Jan 06 22:48:58 2022
$end
$version
	Icarus Verilog
$end
$timescale
	1ns
$end
$scope module BCD_divisible_by_11_tb $end
$var wire 1 ! Q $end
$var reg 16 " D [15:0] $end
$scope module uut $end
$var wire 16 # D [15:0] $end
$var wire 1 ! Q $end
$var wire 6 $ sum3 [5:0] $end
$var wire 6 % sum2 [5:0] $end
$var wire 6 & sum1 [5:0] $end
$var wire 6 ' d3 [5:0] $end
$var wire 6 ( d2 [5:0] $end
$var wire 6 ) d1 [5:0] $end
$var wire 1 * c5 $end
$var wire 1 + c4 $end
$var wire 1 , c3 $end
$var wire 1 - c2 $end
$var wire 1 . c1 $end
$var wire 6 / c [5:0] $end
$var wire 6 0 b3 [5:0] $end
$var wire 6 1 b2 [5:0] $end
$var wire 6 2 b1 [5:0] $end
$var wire 6 3 a [5:0] $end
$scope module add0 $end
$var wire 6 4 D1 [5:0] $end
$var wire 6 5 D2 [5:0] $end
$var wire 6 6 Out [5:0] $end
$var wire 1 . Cout $end
$scope module dig0 $end
$var wire 1 7 Cin $end
$var wire 1 8 Cout $end
$var wire 1 9 D1 $end
$var wire 1 : D12 $end
$var wire 1 ; D1C $end
$var wire 1 < D2 $end
$var wire 1 = D2C $end
$var wire 1 > Out $end
$upscope $end
$scope module dig1 $end
$var wire 1 8 Cin $end
$var wire 1 ? Cout $end
$var wire 1 @ D1 $end
$var wire 1 A D12 $end
$var wire 1 B D1C $end
$var wire 1 C D2 $end
$var wire 1 D D2C $end
$var wire 1 E Out $end
$upscope $end
$scope module dig2 $end
$var wire 1 ? Cin $end
$var wire 1 F Cout $end
$var wire 1 G D1 $end
$var wire 1 H D12 $end
$var wire 1 I D1C $end
$var wire 1 J D2 $end
$var wire 1 K D2C $end
$var wire 1 L Out $end
$upscope $end
$scope module dig3 $end
$var wire 1 F Cin $end
$var wire 1 M Cout $end
$var wire 1 N D1 $end
$var wire 1 O D12 $end
$var wire 1 P D1C $end
$var wire 1 Q D2 $end
$var wire 1 R D2C $end
$var wire 1 S Out $end
$upscope $end
$scope module dig4 $end
$var wire 1 M Cin $end
$var wire 1 T Cout $end
$var wire 1 U D1 $end
$var wire 1 V D12 $end
$var wire 1 W D1C $end
$var wire 1 X D2 $end
$var wire 1 Y D2C $end
$var wire 1 Z Out $end
$upscope $end
$scope module dig5 $end
$var wire 1 T Cin $end
$var wire 1 . Cout $end
$var wire 1 [ D1 $end
$var wire 1 \ D12 $end
$var wire 1 ] D1C $end
$var wire 1 ^ D2 $end
$var wire 1 _ D2C $end
$var wire 1 ` Out $end
$upscope $end
$upscope $end
$scope module add1 $end
$var wire 6 a D1 [5:0] $end
$var wire 6 b D2 [5:0] $end
$var wire 6 c Out [5:0] $end
$var wire 1 - Cout $end
$scope module dig0 $end
$var wire 1 d Cin $end
$var wire 1 e Cout $end
$var wire 1 f D1 $end
$var wire 1 g D12 $end
$var wire 1 h D1C $end
$var wire 1 i D2 $end
$var wire 1 j D2C $end
$var wire 1 k Out $end
$upscope $end
$scope module dig1 $end
$var wire 1 e Cin $end
$var wire 1 l Cout $end
$var wire 1 m D1 $end
$var wire 1 n D12 $end
$var wire 1 o D1C $end
$var wire 1 p D2 $end
$var wire 1 q D2C $end
$var wire 1 r Out $end
$upscope $end
$scope module dig2 $end
$var wire 1 l Cin $end
$var wire 1 s Cout $end
$var wire 1 t D1 $end
$var wire 1 u D12 $end
$var wire 1 v D1C $end
$var wire 1 w D2 $end
$var wire 1 x D2C $end
$var wire 1 y Out $end
$upscope $end
$scope module dig3 $end
$var wire 1 s Cin $end
$var wire 1 z Cout $end
$var wire 1 { D1 $end
$var wire 1 | D12 $end
$var wire 1 } D1C $end
$var wire 1 ~ D2 $end
$var wire 1 !" D2C $end
$var wire 1 "" Out $end
$upscope $end
$scope module dig4 $end
$var wire 1 z Cin $end
$var wire 1 #" Cout $end
$var wire 1 $" D1 $end
$var wire 1 %" D12 $end
$var wire 1 &" D1C $end
$var wire 1 '" D2 $end
$var wire 1 (" D2C $end
$var wire 1 )" Out $end
$upscope $end
$scope module dig5 $end
$var wire 1 #" Cin $end
$var wire 1 - Cout $end
$var wire 1 *" D1 $end
$var wire 1 +" D12 $end
$var wire 1 ," D1C $end
$var wire 1 -" D2 $end
$var wire 1 ." D2C $end
$var wire 1 /" Out $end
$upscope $end
$upscope $end
$scope module add2 $end
$var wire 6 0" D1 [5:0] $end
$var wire 6 1" D2 [5:0] $end
$var wire 6 2" Out [5:0] $end
$var wire 1 , Cout $end
$scope module dig0 $end
$var wire 1 3" Cin $end
$var wire 1 4" Cout $end
$var wire 1 5" D1 $end
$var wire 1 6" D12 $end
$var wire 1 7" D1C $end
$var wire 1 8" D2 $end
$var wire 1 9" D2C $end
$var wire 1 :" Out $end
$upscope $end
$scope module dig1 $end
$var wire 1 4" Cin $end
$var wire 1 ;" Cout $end
$var wire 1 <" D1 $end
$var wire 1 =" D12 $end
$var wire 1 >" D1C $end
$var wire 1 ?" D2 $end
$var wire 1 @" D2C $end
$var wire 1 A" Out $end
$upscope $end
$scope module dig2 $end
$var wire 1 ;" Cin $end
$var wire 1 B" Cout $end
$var wire 1 C" D1 $end
$var wire 1 D" D12 $end
$var wire 1 E" D1C $end
$var wire 1 F" D2 $end
$var wire 1 G" D2C $end
$var wire 1 H" Out $end
$upscope $end
$scope module dig3 $end
$var wire 1 B" Cin $end
$var wire 1 I" Cout $end
$var wire 1 J" D1 $end
$var wire 1 K" D12 $end
$var wire 1 L" D1C $end
$var wire 1 M" D2 $end
$var wire 1 N" D2C $end
$var wire 1 O" Out $end
$upscope $end
$scope module dig4 $end
$var wire 1 I" Cin $end
$var wire 1 P" Cout $end
$var wire 1 Q" D1 $end
$var wire 1 R" D12 $end
$var wire 1 S" D1C $end
$var wire 1 T" D2 $end
$var wire 1 U" D2C $end
$var wire 1 V" Out $end
$upscope $end
$scope module dig5 $end
$var wire 1 P" Cin $end
$var wire 1 , Cout $end
$var wire 1 W" D1 $end
$var wire 1 X" D12 $end
$var wire 1 Y" D1C $end
$var wire 1 Z" D2 $end
$var wire 1 [" D2C $end
$var wire 1 \" Out $end
$upscope $end
$upscope $end
$scope module add3 $end
$var wire 6 ]" D1 [5:0] $end
$var wire 6 ^" D2 [5:0] $end
$var wire 6 _" Out [5:0] $end
$var wire 1 + Cout $end
$scope module dig0 $end
$var wire 1 `" Cin $end
$var wire 1 a" Cout $end
$var wire 1 b" D1 $end
$var wire 1 c" D12 $end
$var wire 1 d" D1C $end
$var wire 1 e" D2 $end
$var wire 1 f" D2C $end
$var wire 1 g" Out $end
$upscope $end
$scope module dig1 $end
$var wire 1 a" Cin $end
$var wire 1 h" Cout $end
$var wire 1 i" D1 $end
$var wire 1 j" D12 $end
$var wire 1 k" D1C $end
$var wire 1 l" D2 $end
$var wire 1 m" D2C $end
$var wire 1 n" Out $end
$upscope $end
$scope module dig2 $end
$var wire 1 h" Cin $end
$var wire 1 o" Cout $end
$var wire 1 p" D1 $end
$var wire 1 q" D12 $end
$var wire 1 r" D1C $end
$var wire 1 s" D2 $end
$var wire 1 t" D2C $end
$var wire 1 u" Out $end
$upscope $end
$scope module dig3 $end
$var wire 1 o" Cin $end
$var wire 1 v" Cout $end
$var wire 1 w" D1 $end
$var wire 1 x" D12 $end
$var wire 1 y" D1C $end
$var wire 1 z" D2 $end
$var wire 1 {" D2C $end
$var wire 1 |" Out $end
$upscope $end
$scope module dig4 $end
$var wire 1 v" Cin $end
$var wire 1 }" Cout $end
$var wire 1 ~" D1 $end
$var wire 1 !# D12 $end
$var wire 1 "# D1C $end
$var wire 1 ## D2 $end
$var wire 1 $# D2C $end
$var wire 1 %# Out $end
$upscope $end
$scope module dig5 $end
$var wire 1 }" Cin $end
$var wire 1 + Cout $end
$var wire 1 &# D1 $end
$var wire 1 '# D12 $end
$var wire 1 (# D1C $end
$var wire 1 )# D2 $end
$var wire 1 *# D2C $end
$var wire 1 +# Out $end
$upscope $end
$upscope $end
$scope module add4 $end
$var wire 6 ,# D1 [5:0] $end
$var wire 6 -# D2 [5:0] $end
$var wire 6 .# Out [5:0] $end
$var wire 1 * Cout $end
$scope module dig0 $end
$var wire 1 /# Cin $end
$var wire 1 0# Cout $end
$var wire 1 1# D1 $end
$var wire 1 2# D12 $end
$var wire 1 3# D1C $end
$var wire 1 4# D2 $end
$var wire 1 5# D2C $end
$var wire 1 6# Out $end
$upscope $end
$scope module dig1 $end
$var wire 1 0# Cin $end
$var wire 1 7# Cout $end
$var wire 1 8# D1 $end
$var wire 1 9# D12 $end
$var wire 1 :# D1C $end
$var wire 1 ;# D2 $end
$var wire 1 <# D2C $end
$var wire 1 =# Out $end
$upscope $end
$scope module dig2 $end
$var wire 1 7# Cin $end
$var wire 1 ># Cout $end
$var wire 1 ?# D1 $end
$var wire 1 @# D12 $end
$var wire 1 A# D1C $end
$var wire 1 B# D2 $end
$var wire 1 C# D2C $end
$var wire 1 D# Out $end
$upscope $end
$scope module dig3 $end
$var wire 1 ># Cin $end
$var wire 1 E# Cout $end
$var wire 1 F# D1 $end
$var wire 1 G# D12 $end
$var wire 1 H# D1C $end
$var wire 1 I# D2 $end
$var wire 1 J# D2C $end
$var wire 1 K# Out $end
$upscope $end
$scope module dig4 $end
$var wire 1 E# Cin $end
$var wire 1 L# Cout $end
$var wire 1 M# D1 $end
$var wire 1 N# D12 $end
$var wire 1 O# D1C $end
$var wire 1 P# D2 $end
$var wire 1 Q# D2C $end
$var wire 1 R# Out $end
$upscope $end
$scope module dig5 $end
$var wire 1 L# Cin $end
$var wire 1 * Cout $end
$var wire 1 S# D1 $end
$var wire 1 T# D12 $end
$var wire 1 U# D1C $end
$var wire 1 V# D2 $end
$var wire 1 W# D2C $end
$var wire 1 X# Out $end
$upscope $end
$upscope $end
$upscope $end
$upscope $end
$enddefinitions $end
#0
$dumpvars
0X#
1W#
1V#
0U#
0T#
0S#
0R#
1Q#
1P#
0O#
0N#
0M#
1L#
0K#
1J#
1I#
0H#
0G#
0F#
1E#
0D#
1C#
1B#
0A#
0@#
0?#
1>#
1=#
1<#
1;#
1:#
19#
18#
17#
06#
05#
14#
03#
12#
11#
10#
0/#
b10 .#
b111111 -#
b11 ,#
0+#
0*#
0)#
0(#
0'#
0&#
0%#
0$#
0##
0"#
0!#
0~"
0}"
0|"
0{"
0z"
0y"
0x"
0w"
0v"
0u"
0t"
0s"
0r"
0q"
0p"
0o"
1n"
0m"
1l"
0k"
0j"
0i"
0h"
1g"
0f"
0e"
0d"
0c"
1b"
0a"
0`"
b11 _"
b10 ^"
b1 ]"
0\"
1["
1Z"
0Y"
0X"
0W"
0V"
1U"
1T"
0S"
0R"
0Q"
1P"
0O"
1N"
1M"
0L"
0K"
0J"
1I"
0H"
1G"
1F"
0E"
0D"
0C"
1B"
0A"
0@"
1?"
0>"
1="
1<"
1;"
1:"
09"
18"
07"
06"
05"
04"
03"
b1 2"
b111111 1"
b10 0"
1/"
0."
0-"
0,"
0+"
1*"
1)"
0("
0'"
0&"
0%"
1$"
0#"
1""
0!"
0~
0}
0|
1{
0z
1y
0x
0w
0v
0u
1t
0s
1r
0q
0p
0o
0n
1m
0l
1k
0j
1i
0h
0g
0f
0e
0d
b111111 c
b1 b
b111110 a
1`
0_
0^
0]
0\
1[
1Z
0Y
0X
0W
0V
1U
0T
1S
0R
0Q
0P
0O
1N
0M
1L
0K
0J
0I
0H
1G
0F
1E
0D
0C
0B
0A
1@
0?
1>
0=
1<
0;
0:
09
08
07
b111111 6
b1 5
b111110 4
b10 3
b1 2
b111110 1
b111111 0
b10 /
0.
0-
1,
0+
1*
b1 )
b111110 (
b111111 '
b1 &
b11 %
b10 $
b10000100100001 #
b10000100100001 "
0!
$end
#20
0:#
00#
16#
02#
b1 $
b1 .#
0=#
19#
0<#
04#
1e
1;#
0k
1g
b111110 '
b111110 c
b111110 -#
1r
1f
0m
b111101 (
b111101 a
b10 )
b10000100100010 "
b10000100100010 #
#40
1*
1V#
0-
0X#
1W#
1/"
0,"
1L#
1P#
0#"
0R#
1Q#
1)"
0&"
1E#
1I#
0z
0K#
1J#
1:#
1<#
1""
0}
1>#
10#
1B#
0s
0D#
1C#
12#
1y
0v
1i"
17#
14#
0e
1;#
0l
1A"
1>"
1@"
06#
b10 $
b10 .#
1=#
19#
1k
0g
b111111 '
b111111 c
b111111 -#
1r
0o
0b"
14"
11#
0a"
18#
0f
1m
b10 &
b10 2"
b10 ]"
0:"
16"
1g"
0c"
b11 %
b11 _"
b11 ,#
1n"
b111110 (
b111110 a
15"
1e"
0l"
b11 3
b11 0"
b1 /
b1 ^"
b1 )
b11000100010001 "
b11000100010001 #
#60
0,
0*
0["
0W#
0P"
0Z"
1.
0L#
0V#
1-
0U"
0`
1]
0Q#
0/"
1,"
0I"
0T"
1T
0E#
0P#
1#"
0N"
0Z
1W
0J#
0)"
1&"
0B"
0M"
1M
0!
0>#
0I#
1z
0G"
0S
1P
0""
1}
0;"
0F"
1F
0B#
1s
0@"
0L
1I
0C#
0=#
0y
1v
1b"
04"
0?"
1?
07#
0;#
1l
09#
1D#
0@#
0A#
1:"
06"
0E
1B
0:#
0<#
0r
1o
08#
1?#
08"
18
00#
04#
1e
0n"
1u"
b0 0
b0 6
b0 1"
0>
1:
b101 $
b101 .#
16#
02#
b0 '
b0 c
b0 -#
0k
1g
0i"
1p"
19
11#
1f
0A"
0="
0>"
b101 &
b101 2"
b101 ]"
1H"
0D"
0E"
b111111 1
b111111 4
b101 %
b101 _"
b101 ,#
1g"
b111111 (
b111111 a
0<"
1C"
0e"
b101 3
b101 0"
b0 2
b0 /
b0 ^"
b0 )
b101000000000000 "
b101000000000000 #
#80
1X#
1S#
1R#
1+#
1M#
1&#
1=#
1K#
1%#
1\"
18#
1F#
1~"
1Z"
0.
1n"
1|"
1V"
1`
0]
0!
1i"
1w"
1T"
0T
1A"
1O"
1Z
0W
1?"
0?
1M"
0M
16#
b111011 $
b111011 .#
0D#
1E
0B
1S
0P
11#
0?#
18"
08
0F"
0F
1g"
b111011 %
b111011 _"
b111011 ,#
0u"
1>
0:
b111011 0
b111011 6
b111011 1"
0L
0I
1b"
0p"
09
0G
1:"
b111011 &
b111011 2"
b111011 ]"
0H"
b111010 1
b111010 4
05"
0C"
b0 3
b0 0"
b101 2
b10100000000 "
b10100000000 #
#100
0&#
0\"
0~"
0Z"
1.
0V"
0`
1]
0X#
0w"
0T"
1T
0S#
0+
0O"
0Z
1W
0R#
0+#
0(#
0M"
1M
0M#
0}"
0S
1P
0K#
0%#
0"#
0i"
1F
0F#
0v"
0A"
1I
0q"
0r"
0|"
0y"
0b"
0?"
1?
0p"
0o"
0:"
0E
1B
b0 &
b0 2"
b0 ]"
0H"
0=#
0t"
08"
18
0F"
08#
0h"
0>
1:
b0 0
b0 6
b0 1"
0L
16#
0n"
0k"
b101 $
b101 .#
1D#
19
1G
11#
0a"
1?#
b111111 1
b111111 4
1g"
0c"
b101 %
b101 _"
b101 ,#
1u"
1e"
1s"
b0 2
b101 /
b101 ^"
b1010000 "
b1010000 #
#120
1X#
1V#
0-
1R#
1/"
0,"
1P#
0#"
1=#
1K#
1)"
0&"
0!
1;#
0l
1I#
0z
1r
0o
1""
0}
14#
0e
0B#
0s
16#
b111011 $
b111011 .#
0D#
1k
0g
b111011 '
b111011 c
b111011 -#
0y
0v
01#
0?#
0f
0t
0g"
b0 %
b0 _"
b0 ,#
0u"
b111010 (
b111010 a
0e"
0s"
b0 /
b0 ^"
b101 )
b101 "
b101 #
#140
0V#
1-
0/"
1,"
0P#
1#"
0O#
0)"
1&"
0I#
1z
0J#
0""
1}
0>#
0*
1s
0N#
0C#
0X#
0W#
1v
18#
1M#
07#
0L#
0;#
1l
1n"
1%#
1=#
0<#
1R#
0Q#
0r
1o
0D#
1a"
1v"
00#
0E#
04#
1e
0B#
1c"
1x"
06#
02#
b10010 $
b10010 .#
0K#
0G#
0k
1g
b0 '
b0 c
b0 -#
0y
1b"
1w"
01#
0F#
1f
1t
1:"
b1001 &
b1001 2"
b1001 ]"
1O"
0g"
b10010 %
b10010 _"
b10010 ,#
0|"
b111111 (
b111111 a
15"
1J"
1e"
1z"
b1001 3
b1001 0"
b1001 /
b1001 ^"
b0 )
b1001000010010000 "
b1001000010010000 #
#160
1>#
1*
1C#
1@#
1A#
1W#
1T#
1U#
17#
1?#
1L#
1S#
1<#
19#
1:#
1u"
0Q#
1N#
0O#
1+#
10#
1p"
0E#
1&#
12#
1H"
0G#
1\"
1D#
1X#
1i"
1F"
0F
1~"
1Z"
0.
1B#
0s
1V#
0-
1A"
1L
0I
1V"
1`
0]
1y
0v
1/"
0,"
1?"
0?
1T"
0T
1;#
0l
1P#
0#"
1E
0B
1Z
0W
1=#
0R#
1r
0o
1)"
0&"
18"
08
0M"
0M
18#
1M#
14#
0e
0I#
0z
1>
0:
b110111 0
b110111 6
b110111 1"
0S
0P
06#
1n"
b101110 $
b101110 .#
1K#
1%#
1k
0g
b110111 '
b110111 c
b110111 -#
0""
0}
1b"
0w"
09
0N
11#
0a"
0F#
0v"
0f
0{
1:"
b110111 &
b110111 2"
b110111 ]"
0O"
b110110 1
b110110 4
1g"
0c"
b110111 %
b110111 _"
b110111 ,#
0|"
0x"
b110110 (
b110110 a
05"
0J"
0e"
0z"
b0 3
b0 0"
b1001 2
b0 /
b0 ^"
b1001 )
b100100001001 "
b100100001001 #
#180
1!
0X#
1*
0T#
0U#
1W#
0S#
0+
0&#
1,
1L#
0N#
0+#
0(#
0K#
0\"
1["
0M#
0}"
0~"
1P"
0%#
0"#
0V"
1U"
0R#
0O#
1Q#
0v"
1I"
17#
1>#
1E#
0r"
0y"
1N"
0H#
0<#
0C#
0G#
1J#
0w"
0?"
0F"
1M"
10#
0F#
0;#
0B#
1I#
1>"
0@"
1E"
0G"
0O"
0E
0L
b111001 0
b111001 6
b111001 1"
1S
06#
12#
0m"
0=#
09#
1:#
0t"
b0 $
b0 .#
0D#
0@#
1A#
0|"
0r
0y
b111001 '
b111001 c
b111001 -#
1""
0b"
14"
0i"
1;"
0p"
1B"
0@
0G
1N
11#
0a"
18#
0h"
1?#
0o"
0m
0t
1{
0:"
16"
0A"
0="
b0 &
b0 2"
b0 ]"
0H"
0D"
b111000 1
b111000 4
1g"
0c"
1n"
0j"
b111 %
b111 _"
b111 ,#
1u"
0q"
b111000 (
b111000 a
15"
1<"
1C"
1e"
1l"
1s"
b111 3
b111 0"
b111 2
b111 /
b111 ^"
b111 )
b111011101110111 "
b111011101110111 #
#200
1H#
1*
0X#
1W#
1L#
1G"
1C#
0R#
1Q#
1!
1E#
1@"
09#
1<#
0@#
0K#
0J#
1F#
1?"
1F"
17#
1>#
1;#
1B#
0I#
1N"
1|"
1E
b111111 0
b111111 6
b111111 1"
1L
0=#
0:#
b0 $
b0 .#
0D#
0A#
1r
1y
b110111 '
b110111 c
b110111 -#
0""
0i"
1;"
0p"
1B"
1w"
1@
1G
08#
0?#
1m
1t
0{
0A"
0>"
0H"
0E"
b1000 &
b1000 2"
b1000 ]"
1O"
1K"
1L"
b111110 1
b111110 4
0n"
b1001 %
b1001 _"
b1001 ,#
0u"
b110110 (
b110110 a
0<"
0C"
1J"
0l"
0s"
b1001 3
b1001 0"
b1 2
b1 /
b1 ^"
b1001 )
b1001000100011001 "
b1001000100011001 #
